README.md
setup.cfg
setup.py
IntexfyLibs/__init__.py
IntexfyLibs/intexfy_instance.py
IntexfyLibs/intexfy_logger.py
IntexfyLibs/intexfy_sendmail.py
IntexfyLibs.egg-info/PKG-INFO
IntexfyLibs.egg-info/SOURCES.txt
IntexfyLibs.egg-info/dependency_links.txt
IntexfyLibs.egg-info/requires.txt
IntexfyLibs.egg-info/top_level.txt