Metadata-Version: 1.0
Name: IntexfyLibs
Version: 0.0.10
Summary: Package with intexfy libs
Home-page: UNKNOWN
Author: Heitor Tancredo
Author-email: heitor@intexfy.com
License: UNKNOWN
Keywords: Intexfy Libs
Platform: UNKNOWN
